config_lang_reader-0.1.1.dist-info/METADATA
config_lang_reader-0.1.1.dist-info/WHEEL
config_lang_reader/__init__.py
config_lang_reader/__init__.pyi
config_lang_reader/config_lang_reader.pyd
config_lang_reader/py.typed
config_lang_reader-0.1.1.dist-info/RECORD
