Metadata-Version: 2.4
Name: config_lang_reader
Version: 0.1.1
Classifier: Programming Language :: Rust
Classifier: Programming Language :: Python :: Implementation :: CPython
Classifier: Programming Language :: Python :: Implementation :: PyPy
Summary: A Rust library and Python extension for reading and converting configuration files (TOML, YAML, JSON, XML) into Python dictionaries. Powered by PyO3.
Author: Guangyu He <fredhgy2010@gmail.com>
Author-email: Guangyu He <fredhgy2010@gmail.com>
Requires-Python: >=3.8
